{
  "addressList": [
    {
      "city": "Toronto",
      "country": "Canada",
      "fullAddress": "744 Mount Pleasant Road Toronto Ontario",
      "latitudeCoordinate": "43.707166169",
      "longitudeCoordinate": "-79.390010242",
      "postalCode": "M4S 2N6",
      "province": "Ontario",
      "streetAddress": "744 Mount Pleasant Road"
    },
    {
      "city": "Toronto",
      "country": "Canada",
      "fullAddress": "746 Mount Pleasant Road Toronto Ontario",
      "latitudeCoordinate": "43.707186582",
      "longitudeCoordinate": "-79.390018183",
      "postalCode": "M4S 2N6",
      "province": "Ontario",
      "streetAddress": "746 Mount Pleasant Road"
    },
    {
      "city": "Toronto",
      "country": "Canada",
      "fullAddress": "748 Mount Pleasant Road Toronto Ontario",
      "latitudeCoordinate": "43.707206995",
      "longitudeCoordinate": "-79.390026136",
      "postalCode": "M4S 2N6",
      "province": "Ontario",
      "streetAddress": "748 Mount Pleasant Road"
    },
    {
      "city": "Toronto",
      "country": "Canada",
      "fullAddress": "750 Mount Pleasant Road Toronto Ontario",
      "latitudeCoordinate": "43.707227408",
      "longitudeCoordinate": "-79.390034078",
      "postalCode": "M4S 2N6",
      "province": "Ontario",
      "streetAddress": "750 Mount Pleasant Road"
    },
    {
      "city": "Toronto",
      "country": "Canada",
      "fullAddress": "752 Mount Pleasant Road Toronto Ontario",
      "latitudeCoordinate": "43.70724783",
      "longitudeCoordinate": "-79.390042031",
      "postalCode": "M4S 2N6",
      "province": "Ontario",
      "streetAddress": "752 Mount Pleasant Road"
    },
    {
      "city": "Toronto",
      "country": "Canada",
      "fullAddress": "756 Mount Pleasant Road Toronto Ontario",
      "latitudeCoordinate": "43.707288646",
      "longitudeCoordinate": "-79.390057914",
      "postalCode": "M4S 2N6",
      "province": "Ontario",
      "streetAddress": "756 Mount Pleasant Road"
    },
    {
      "city": "Toronto",
      "country": "Canada",
      "fullAddress": "758 Mount Pleasant Road Toronto Ontario",
      "latitudeCoordinate": "43.707330432",
      "longitudeCoordinate": "-79.39025907",
      "postalCode": "M4S 2N6",
      "province": "Ontario",
      "streetAddress": "758 Mount Pleasant Road"
    }
  ],
  "backgroundInformationList": [
    {
      "description": "Notice of Application - Under the Planning Act - 744, 746, 748, 750, 752, 756 and 758 Mount Pleasant Road",
      "url": "https://secure.toronto.ca/nm/api/individual/fileSpace.do?f=7590"
    }
  ],
  "contact": {
    "city": "Toronto",
    "contactName": "Registrar Secretariat",
    "country": "Canada",
    "emailAddress": "RegistrarCCO@toronto.ca",
    "locationName": "Toronto City Hall",
    "phone": "416-394-8101",
    "postalCode": "M5H 2N2",
    "province": "ON",
    "streetAddress": "100 Queen Street"
  },
  "decisionBody": "Toronto and East York Community Council",
  "eventList": [],
  "noticeDate": 1782446400000,
  "noticeDescription": "<p style=\"text-align: center;\"><strong>NOTICE OF APPLICATION(S)</strong></p>\n<p style=\"text-align: center;\"><strong>(Under the Planning Act)</strong></p>\n<p>&nbsp;</p>\n<p>The City has received the following application(s) under the Planning Act:</p>\n<p>&nbsp;</p>\n<p><strong>TORONTO AND EAST YORK COMMUNITY COUNCIL AREA:</strong></p>\n<p>&nbsp;</p>\n<p>Application Number: 26 149124 STE 12 OZ</p>\n<p>Application to Amend the Zoning By-Law to allow for the development of a 56-storey mixed-use building, which includes 618 new residential units and 65 m<sup>2</sup> of non-residential gross floor area at grade.</p>\n<p>744, 746, 748, 750, 752, 756 and 758 Mount Pleasant Road</p>\n<p>Ward 12 &ndash; Toronto-St. Paul's</p>\n<p>Patrick Miller, Planner at 416-338-3002 or <a href=\"mailto:Patrick.Miller@toronto.ca\">Patrick.Miller@toronto.ca</a>.</p>\n<p>&nbsp;</p>\n<p><strong>CONTACT INFORMATION</strong></p>\n<p>&nbsp;</p>\n<p>City Clerk, Attention: Registrar Secretariat</p>\n<p>Toronto City Hall, 2nd Floor West, 100 Queen Street West, Toronto, ON, M5H 2N2,</p>\n<p>Tel: 416-394-8101, Email: <a href=\"mailto:RegistrarCCO@toronto.ca\">RegistrarCCO@toronto.ca</a>.</p>\n<p>&nbsp;</p>\n<p><strong>BACKGROUND INFORMATION</strong></p>\n<p>&nbsp;</p>\n<p>Background information and materials regarding the above-listed proposals are available at <a href=\"http://www.toronto.ca/city-government/planning-development/application-information-centre/\">www.toronto.ca/city-government/planning-development/application-information-centre/</a>.<br />&nbsp;</p>\n<p><strong>FURTHER INFORMATION</strong></p>\n<p>&nbsp;</p>\n<p>If you wish to receive notice regarding the progression of any of the proposed applications above, which include Official Plan amendment, proposed Draft Plan of Subdivision, Draft Plan of Common Elements Condominium, Vacant Land Condominium Application and/or proposed Zoning By-law amendment, you may make a request to the City Clerk, to the attention of the Registrar Secretariat, at the address or email noted above.</p>\n<p>&nbsp;</p>",
  "noticeHeadingType": "Public Notice",
  "noticeId": 7621,
  "otherReferenceList": [],
  "planningApplicationNumbers": [
    "26 149124 STE 12 OZ"
  ],
  "signedBy": "John D. Elvidge, City Clerk",
  "title": "Notice of Application - Under the Planning Act - 744, 746, 748, 750, 752, 756 and 758 Mount Pleasant Road",
  "topics": [
    "Planning > Complete application for Zoning By-law Amendment"
  ],
  "uniqueMapUrl": [
    "https://www.toronto.ca/legdocs/nmis/legend/images/legend-planning.png"
  ]
}
